{
	"$schema": "https://raw.githubusercontent.com/xen-42/outer-wilds-new-horizons/main/NewHorizons/Schemas/body_schema.json",
	"name" : "Triton",
	"starSystem" : "xen.RealSolarSystem",
	"Base" :
	{
		"surfaceGravity" : 4,
		"surfaceSize" : 65,
		"hasMapMarker" : true
	},
	"Orbit" :
	{
		"semiMajorAxis" : 1200,
		"inclination" : 130,
		"longitudeOfAscendingNode": 0,
		"primaryBody" : "Neptune",
		"isMoon" : true,
		"isTidallyLocked" : true,
		"axialTilt": 220,
		"alignmentAxis": {"x": -1, "y": 0, "z": 0}
	},
	"HeightMap" :
	{
		"heightMap" : "planets/assets/triton_heightmap.png",	
		"textureMap" : "planets/assets/triton_texturemap.png",	
		"minHeight" : 63,
		"maxHeight" : 65
	},
	"ShipLog" : {
		"spriteFolder": "planets/shiplogs/sprites",
		"mapMode" : {
			"revealedSprite": "planets/shiplogs/icons/Triton log.png"
		}
	}
}