{
	"$schema": "https://raw.githubusercontent.com/Outer-Wilds-New-Horizons/new-horizons/main/NewHorizons/Schemas/body_schema.json",
	"name" : "Styx",
	"starSystem" : "xen.RealSolarSystem",
	"Base" :
	{
		"surfaceGravity" : 1,
		"surfaceSize" : 10
	},
	"MapMarker":
	{
		"enabled": true
	},
	"Orbit" :
	{
		"semiMajorAxis" : 500,
		"primaryBody" : "Pluto-Charon",
		"inclination": 120,
		"trueAnomaly": 135,
		"isMoon" : true,
		"siderealPeriod": -2.5,
		"axialTilt": 320,
		"tint": {
            "r": 175,
            "g": 175,
            "b": 175,
            "a": 255
        }
	},
	"ProcGen": {
		"scale": 8,
		"color": {
			"r": 100,
			"g": 100,
			"b": 100,
			"a": 255
		}
	},
	"ShipLog" : {
		"spriteFolder": "planets/shiplogs/sprites",
		"mapMode" : {
			"revealedSprite": "planets/shiplogs/icons/Styx log.png"
		}
	}
}